immunoforge/__init__.py
immunoforge/alleles.py
immunoforge/analyzer.py
immunoforge/config.py
immunoforge/finder.py
immunoforge/utils.py
immunoforge/tools/__init__.py
immunoforge/tools/base.py
immunoforge/tools/deepimmuno.py
immunoforge/tools/iedb.py
immunoforge/tools/mhcflurry.py
immunoforge/tools/netchop.py
immunoforge/tools/netmhcpan.py
immunoforge-0.1.2.dist-info/METADATA
immunoforge-0.1.2.dist-info/WHEEL
immunoforge-0.1.2.dist-info/entry_points.txt
immunoforge-0.1.2.dist-info/top_level.txt
immunoforge-0.1.2.dist-info/RECORD
